hatch_gettext/__about__.py
hatch_gettext/__init__.py
hatch_gettext/hooks.py
hatch_gettext/plugin.py
hatch_gettext/py.typed
hatch_gettext-1.1.0.dist-info/METADATA
hatch_gettext-1.1.0.dist-info/WHEEL
hatch_gettext-1.1.0.dist-info/entry_points.txt
hatch_gettext-1.1.0.dist-info/licenses/LICENSE.txt
hatch_gettext-1.1.0.dist-info/RECORD
