Metadata-Version: 2.3
Name: hatch-gettext
Version: 1.1.0
Summary: Hatch build hook plugin for GNU gettext
Project-URL: Documentation, https://github.com/damonlynch/hatch-gettext#readme
Project-URL: Issues, https://github.com/damonlynch/hatch-gettext/issues
Project-URL: Homepage, https://github.com/damonlynch/hatch-gettext
Author-email: Damon Lynch <damonlynch@gmail.com>
License-Expression: GPL-3.0-or-later
License-File: LICENSE.txt
Keywords: build,gettext,hatch,i18n,plugin,typing
Classifier: Development Status :: 5 - Production/Stable
Classifier: Framework :: Hatch
Classifier: Programming Language :: Python
Classifier: Programming Language :: Python :: 3.10
Classifier: Programming Language :: Python :: 3.11
Classifier: Programming Language :: Python :: 3.12
Classifier: Programming Language :: Python :: Implementation :: CPython
Classifier: Programming Language :: Python :: Implementation :: PyPy
Classifier: Typing :: Typed
Requires-Python: >=3.10
Requires-Dist: rich
